{
    "x": [
        645.8482007426328,
        0.0,
        666.9585929474094,
        0.0,
        663.1178620408323
    ],
    "y": [
        0.009200361117025437,
        0.001679776526603273,
        -0.002292997574267864,
        0.0004303847169037992,
        -0.016392322092632063
    ],
    "initial_params": [
        645.8482007426328,
        0.0,
        666.9585929474094,
        0.0,
        663.1178620408323,
        0.009200361117025437,
        0.001679776526603273,
        -0.002292997574267864,
        0.0004303847169037992,
        -0.016392322092632063
    ],
    "residuals": {
        "expression": "np.concatenate((params[:9].reshape((3, 3)).flatten(), params[9:])) - np.concatenate((x, y))",
        "variables": [
            "params",
            "x",
            "y"
        ]
    },
    "additional_params": {
        "method": "lm"
    }
}